unitment/__init__.py
unitment-0.0.9.dist-info/METADATA
unitment-0.0.9.dist-info/WHEEL
unitment-0.0.9.dist-info/licenses/LICENSE
unitment-0.0.9.dist-info/RECORD
