Metadata-Version: 2.1
Name: unitment
Version: 0.0.9
Summary: Dynamic unit management.
Project-URL: Homepage, https://github.com/TristynAlxander/unitment
Project-URL: Bug Tracker, https://github.com/TristynAlxander/unitment/issues
Author-email: "Tristin Alexander S." <trystyn.alxander@gmail.com>
License-File: LICENSE
Keywords: measure,measurement,measurements,measures,unit,units
Classifier: License :: OSI Approved :: MIT License
Classifier: Operating System :: OS Independent
Classifier: Programming Language :: Python :: 3
Requires-Python: >=3.7
